Metadata-Version: 2.1
Name: topsis-102017134
Version: 0.3
Summary: topsis package for MCDM problems
Home-page: https://github.com/sri-soumya/topsis
Author: Soumya Srivastava
Author-email: ssrivastava_be20@thapar.edu
License: UNKNOWN
Platform: UNKNOWN
Classifier: Programming Language :: Python :: 3
Classifier: Programming Language :: Python :: 3.6
Classifier: Programming Language :: Python :: 3.7
Classifier: License :: OSI Approved :: MIT License
Classifier: Operating System :: OS Independent
Requires-Python: >=3.0
License-File: LICENSE.txt
